eazysvn.py
eazysvn-1.17.0.dist-info/licenses/COPYING
eazysvn-1.17.0.dist-info/METADATA
eazysvn-1.17.0.dist-info/WHEEL
eazysvn-1.17.0.dist-info/entry_points.txt
eazysvn-1.17.0.dist-info/top_level.txt
eazysvn-1.17.0.dist-info/RECORD
